img360_transformer/__init__.py
img360_transformer/batch_process.py
img360_transformer/gui.py
img360_transformer/utils.py
img360_transformer-0.1.1.dist-info/LICENSE
img360_transformer-0.1.1.dist-info/METADATA
img360_transformer-0.1.1.dist-info/WHEEL
img360_transformer-0.1.1.dist-info/RECORD
