Metadata-Version: 2.3
Name: img360-transformer
Version: 0.1.1
Summary: `img360_transformer` is a Python tool for batch processing and recentering 360-degree images. It provides both a command-line interface and a graphical user interface for ease of use.
License: Apache License
Author: Starmania
Author-email: wycvhrt6vzscfpedxr@gmail.com
Requires-Python: >=3.11
Classifier: Development Status :: 4 - Beta
Classifier: Intended Audience :: End Users/Desktop
Classifier: Intended Audience :: Developers
Classifier: Topic :: Multimedia :: Graphics
Classifier: Topic :: Multimedia :: Graphics :: Graphics Conversion
Classifier: License :: OSI Approved :: Apache Software License
Requires-Dist: opencv-python (>=4.0.0.0,<5.0.0.0)
